{"sections":{"main":{"type":"main-contact","blocks":{"name":{"type":"name_input","settings":{"half_width":true}},"email":{"type":"email_input","settings":{"half_width":true}},"message":{"type":"message_input","settings":{"half_width":false}}},"block_order":["name","email","message"],"disabled":true,"settings":{"show_page_title":false,"use_columns":false,"contact_title":"","contact_text":""}},"image_with_text_overlay_JppCAk":{"type":"image-with-text-overlay","blocks":{"subheading_ik3kYk":{"type":"subheading","settings":{"subheading":"Monthly"}},"heading_L7eGXM":{"type":"heading","settings":{"title":"Circular Q&A","heading_max_width":15,"title_size":84,"title_size_mobile":32,"use_h1":false}},"text_7rTxFV":{"type":"text","settings":{"text":"<p>With Bert & Adele<\/p>","enlarge_text":true}}},"block_order":["subheading_ik3kYk","heading_L7eGXM","text_7rTxFV"],"settings":{"image":"shopify:\/\/shop_images\/MUD-Jeans-Circular-Q-A.png","height":"fixed","height_desktop":600,"height_mobile":460,"image_link":"","full_width":true,"text_alignment":"center center","mobile_overlay_under":false,"overlay_style":"shadow"}},"contact_form_MMWrYe":{"type":"contact-form","blocks":{"name_input_BeRUB6":{"type":"name_input","settings":{"half_width":false}},"custom_input_FeG6k3":{"type":"custom_input","settings":{"title":"Last name","type":"text","required":true,"half_width":false}},"email_input_HbrWet":{"type":"email_input","settings":{"half_width":false}}},"block_order":["name_input_BeRUB6","custom_input_FeG6k3","email_input_HbrWet"],"settings":{"contact_title":"Circular Q&A","contact_text":"<p>Currently writing a paper or thesis and have a specific question to ask? Join our monthly Circular Q&A and ask our Founder Bert van Son or our CSR Officer Adele Cortese all things circular.<\/p>","color_scheme":"1"}},"newsletter_cWRxaC":{"type":"newsletter","settings":{"title":"Subscribe to our newsletter","subheading":"<p>Be the first to get exclusive deals, new denim drops, and latest circular fashion insights—straight to your inbox.<\/p>","color_scheme":"default"}}},"order":["main","image_with_text_overlay_JppCAk","contact_form_MMWrYe","newsletter_cWRxaC"]}